main.py
pyquest/__init__.py
pyquest/config.py
pyquest/core.py
pyquest/engine.py
pyquest/errors.py
pyquest/events.py
pyquest/demos/demo.py
pyquest_engine-0.2.0.dist-info/METADATA
pyquest_engine-0.2.0.dist-info/WHEEL
pyquest_engine-0.2.0.dist-info/licenses/LICENSE
pyquest_engine-0.2.0.dist-info/RECORD
