Metadata-Version: 2.1
Name: pyquest-engine
Version: 0.2.0
Summary: Powerful and flexible text game engine.
Project-URL: Homepage, https://github.com/saharking1298/PyQuest
Project-URL: Bug Tracker, https://github.com/saharking1298/PyQuest/issues
Author-email: Sahar Lando <saharlan500@gmail.com>
License-Expression: MIT
License-File: LICENSE
Classifier: Environment :: Console
Classifier: License :: OSI Approved :: MIT License
Classifier: Operating System :: OS Independent
Classifier: Programming Language :: Python :: 3
Classifier: Topic :: Games/Entertainment :: Role-Playing
Requires-Python: >=3.6
